anime_api_scraper/__init__.py
anime_api_scraper/models/data_models.py
anime_api_scraper/processors/animeflv_processors.py
anime_api_scraper/processors/base_processors.py
anime_api_scraper/scraper/animeflv_scraper.py
anime_api_scraper/scraper/base_scraper.py
anime_api_scraper/services/animeflv_services.py
anime_api_scraper/services/base_services.py
anime_api_scraper/utils/exception.py
anime_api_scraper-1.0.1.dist-info/licenses/LICENSE
anime_api_scraper-1.0.1.dist-info/METADATA
anime_api_scraper-1.0.1.dist-info/WHEEL
anime_api_scraper-1.0.1.dist-info/top_level.txt
anime_api_scraper-1.0.1.dist-info/RECORD
