Metadata-Version: 2.4
Name: anime_api_scraper
Version: 1.0.1
Summary: Scraper robusto para extraer información de sitios de anime, comenzando con AnimeFlv
Author-email: DSt3v3n <haroldsabogal48@gmail.com>
License: MIT
Project-URL: Homepage, https://github.com/dst3v3n/Anime-Api
Project-URL: Documentation, https://github.com/dst3v3n/Anime-Api#readme
Project-URL: Repository, https://github.com/dst3v3n/Anime-Api.git
Project-URL: Bug Tracker, https://github.com/dst3v3n/Anime-Api/issues
Keywords: anime,scraper,web-scraping,animeflv,streaming
Classifier: Development Status :: 4 - Beta
Classifier: Intended Audience :: Developers
Classifier: License :: OSI Approved :: MIT License
Classifier: Operating System :: OS Independent
Classifier: Programming Language :: Python :: 3
Classifier: Programming Language :: Python :: 3.8
Classifier: Programming Language :: Python :: 3.9
Classifier: Programming Language :: Python :: 3.10
Classifier: Programming Language :: Python :: 3.11
Classifier: Programming Language :: Python :: 3.12
Classifier: Topic :: Internet :: WWW/HTTP :: Dynamic Content
Classifier: Topic :: Software Development :: Libraries :: Python Modules
Requires-Python: >=3.8
License-File: LICENSE
Requires-Dist: beautifulsoup4>=4.11.0
Requires-Dist: cloudscraper>=1.2.60
Requires-Dist: requests>=2.28.0
Requires-Dist: lxml>=4.9.0
Provides-Extra: dev
Requires-Dist: pytest>=7.0.0; extra == "dev"
Requires-Dist: pytest-cov>=4.0.0; extra == "dev"
Requires-Dist: black>=22.0.0; extra == "dev"
Requires-Dist: flake8>=5.0.0; extra == "dev"
Requires-Dist: mypy>=0.991; extra == "dev"
Dynamic: license-file
